Metadata-Version: 2.1
Name: sentry-msteams-plugin
Version: 0.3.0
Summary: Sentry plugin for sending events to Microsoft Teams
Home-page: https://github.com/kingcody/sentry-msteams-plugin
Author: Cody Mize
License: GPLv2
Platform: UNKNOWN
Classifier: Intended Audience :: Developers
Classifier: Intended Audience :: System Administrators
Classifier: Operating System :: OS Independent
Classifier: Topic :: Software Development
License-File: LICENSE
Requires-Dist: sentry
